{
  "Global": {
    "By Reinforcement Material Type": {
      "Glass Fiber Reinforced Polymer Poles": {},
      "Hybrid Fiber Reinforced Polymer Poles": {},
      "Other Advanced Composite Poles (Carbon Fiber, Basalt Fiber, Aramid Fiber, etc.)": {}
    },
    "By Structure Configuration": {
      "Single-Pole Structures": {},
      "H-Frame Structures": {},
      "Multi-Pole Portal Structures": {}
    },
    "By Support Method": {
      "Self-Supporting Pole Structures": {},
      "Guyed Pole Structures": {}
    },
    "By Pole Line Function": {
      "Tangent Utility Poles": {},
      "Angle Utility Poles": {},
      "Dead-End and Anchor Utility Poles": {},
      "Terminal and Take-Off Utility Poles": {}
    },
    "By High-Voltage Transmission Poles": {
      "69 kV to 230 kV": {},
      "Above 230 kV": {}
    },
    "By Installation Type": {
      "New Transmission Line Construction": {},
      "Transmission Pole Replacement and Retrofit": {}
    },
    "By Operating Environment": {
      "Normal Inland Transmission Corridors": {},
      "Coastal and Corrosion-Prone Transmission Corridors": {},
      "High-Wind and Storm-Prone Transmission Corridors": {},
      "Wildfire-Prone Transmission Corridors": {},
      "Remote and Difficult-Terrain Transmission Corridors": {}
    },
    "By Customer Type": {
      "Transmission System Operators and Transmission Utilities": {},
      "Distribution Network Operators": {},
      "EPC and Grid Infrastructure Contractors": {},
      "Industrial Power Network Owners": {},
      "Government and Public Transmission Agencies": {}
    },
    "By Region": {
      "UK": {}
    }
  }
}